gw_frequencies/__init__.py
gw_frequencies/multibanding.py
gw_frequencies-0.1.1.dist-info/LICENSE
gw_frequencies-0.1.1.dist-info/WHEEL
gw_frequencies-0.1.1.dist-info/METADATA
gw_frequencies-0.1.1.dist-info/RECORD
