Metadata-Version: 2.1
Name: gw-frequencies
Version: 0.1.1
Summary: A convenience package to make reduced frequency arrays for the representation of gravitational waveforms.
Home-page: https://github.com/jacopok/gw_frequencies
License: GNU GPL3
Keywords: python,gravitational-waves,scientific
Author: jacopok
Author-email: jacopok@gmail.com
Requires-Python: >=3.8,<3.11
Classifier: License :: Other/Proprietary License
Classifier: Programming Language :: Python :: 3
Classifier: Programming Language :: Python :: 3.10
Classifier: Programming Language :: Python :: 3.8
Classifier: Programming Language :: Python :: 3.9
Requires-Dist: numpy (>=1.20,<2.0)
Project-URL: Repository, https://github.com/jacopok/gw_frequencies
